odesli_cli/__init__.py
odesli_cli/odesli_cli.py
odesli_cli-0.0.3.dist-info/LICENSE
odesli_cli-0.0.3.dist-info/METADATA
odesli_cli-0.0.3.dist-info/WHEEL
odesli_cli-0.0.3.dist-info/entry_points.txt
odesli_cli-0.0.3.dist-info/top_level.txt
odesli_cli-0.0.3.dist-info/RECORD
