Metadata-Version: 2.1
Name: odesli-cli
Version: 0.0.3
Summary: CLI client for the Odesli/Songlink API.
Home-page: https://github.com/fabian-thomas/odesli-cli
Author: Fabian Thomas
Author-email: fabian@fabianthomas.de
License: UNKNOWN
Project-URL: Bug Tracker, https://github.com/fabian-thomas/odesli-cli/issues
Platform: UNKNOWN
Classifier: Programming Language :: Python :: 3
Classifier: License :: OSI Approved :: MIT License
Classifier: Operating System :: OS Independent
Requires-Python: >=3.6
License-File: LICENSE
Requires-Dist: odesli
